flashtts/__init__.py
flashtts/import_utils.py
flashtts/logger.py
flashtts/audio/__init__.py
flashtts/audio/base_model.py
flashtts/audio/batch_processor.py
flashtts/audio/utils.py
flashtts/audio/detokenizer/__init__.py
flashtts/audio/detokenizer/snac_detokenizer.py
flashtts/audio/detokenizer/spark_detokenizer.py
flashtts/audio/tokenizer/__init__.py
flashtts/audio/tokenizer/mega_tokenizer.py
flashtts/audio/tokenizer/spark_tokenizer.py
flashtts/commands/__init__.py
flashtts/commands/flashtts_cli.py
flashtts/commands/infer.py
flashtts/commands/serve.py
flashtts/commands/utils.py
flashtts/engine/__init__.py
flashtts/engine/auto_engine.py
flashtts/engine/base_engine.py
flashtts/engine/mega_engine.py
flashtts/engine/orpheus_engine.py
flashtts/engine/spark_engine.py
flashtts/engine/utils.py
flashtts/llm/__init__.py
flashtts/llm/base_llm.py
flashtts/llm/init_llm.py
flashtts/llm/llama_cpp_generator.py
flashtts/llm/mlx_lm_generator.py
flashtts/llm/sglang_generator.py
flashtts/llm/torch_generator.py
flashtts/llm/trtllm_generator.py
flashtts/llm/vllm_generator.py
flashtts/modules/__init__.py
flashtts/modules/blocks/__init__.py
flashtts/modules/blocks/layers.py
flashtts/modules/blocks/samper.py
flashtts/modules/blocks/vocos.py
flashtts/modules/encoder_decoder/__init__.py
flashtts/modules/encoder_decoder/feat_decoder.py
flashtts/modules/encoder_decoder/feat_encoder.py
flashtts/modules/encoder_decoder/wave_generator.py
flashtts/modules/fsq/__init__.py
flashtts/modules/fsq/finite_scalar_quantization.py
flashtts/modules/fsq/residual_fsq.py
flashtts/modules/mega_modules/__init__.py
flashtts/modules/mega_modules/ph_tone_convert.py
flashtts/modules/mega_modules/text_encoder.py
flashtts/modules/mega_modules/utils.py
flashtts/modules/mega_modules/whisper_small.py
flashtts/modules/mega_modules/ar_dur/__init__.py
flashtts/modules/mega_modules/ar_dur/ar_dur_predictor.py
flashtts/modules/mega_modules/ar_dur/layers.py
flashtts/modules/mega_modules/ar_dur/ling_dict.py
flashtts-0.1.7.dist-info/METADATA
flashtts-0.1.7.dist-info/WHEEL
flashtts-0.1.7.dist-info/entry_points.txt
flashtts-0.1.7.dist-info/top_level.txt
flashtts-0.1.7.dist-info/RECORD
