Metadata-Version: 2.4
Name: flashtts
Version: 0.1.7
Summary: A Fast TTS toolkit
Home-page: https://github.com/HuiResearch/FlashTTS
Author: HuangHui
Author-email: m13021933043@163.com
License: MIT
Keywords: flashtts,tts,sparktts,spark-tts,megatts3,orpheus-tts,vllm,sglang,llama-cpp
Classifier: Development Status :: 4 - Beta
Classifier: Intended Audience :: Developers
Classifier: Programming Language :: Python :: 3
Classifier: License :: OSI Approved :: MIT License
Classifier: Operating System :: OS Independent
Requires-Python: >=3.10
Requires-Dist: einops
Requires-Dist: einx
Requires-Dist: omegaconf
Requires-Dist: soundfile
Requires-Dist: soxr
Requires-Dist: transformers
Requires-Dist: fastapi
Requires-Dist: uvicorn
Requires-Dist: httpx
Requires-Dist: snac
Requires-Dist: av
Requires-Dist: librosa
Requires-Dist: pyloudnorm
Requires-Dist: openai-whisper
Requires-Dist: python-multipart
Requires-Dist: WeTextProcessing==1.0.4.1
Dynamic: author
Dynamic: author-email
Dynamic: classifier
Dynamic: description
Dynamic: description-content-type
Dynamic: home-page
Dynamic: keywords
Dynamic: license
Dynamic: requires-dist
Dynamic: requires-python
Dynamic: summary
